flask_download_btn/__init__.py
flask_download_btn/download_btn_mixin.py
flask_download_btn/templates/download_btn/button.html
flask_download_btn/templates/download_btn/progress.html
flask_download_btn/templates/download_btn/script.html
flask_download_btn-0.0.22.dist-info/LICENSE
flask_download_btn-0.0.22.dist-info/METADATA
flask_download_btn-0.0.22.dist-info/WHEEL
flask_download_btn-0.0.22.dist-info/top_level.txt
flask_download_btn-0.0.22.dist-info/RECORD
