Metadata-Version: 2.1
Name: flask-download-btn
Version: 0.0.22
Summary: Defines a SQLALchemy Mixin for creating Bootstrap download buttons in a Flask application.
Home-page: https://dsbowen.github.io/flask-download-btn/
Author: Dillon Bowen
Author-email: dsbowen@wharton.upenn.edu
License: UNKNOWN
Platform: UNKNOWN
Classifier: Programming Language :: Python :: 3
Classifier: License :: OSI Approved :: MIT License
Classifier: Operating System :: OS Independent
Requires-Python: >=3.6
